pywe_sign/__init__.py
pywe_sign/sign.py
pywe_sign-1.1.0.dist-info/METADATA
pywe_sign-1.1.0.dist-info/WHEEL
pywe_sign-1.1.0.dist-info/top_level.txt
pywe_sign-1.1.0.dist-info/RECORD
